ssb_dash_framework/__init__.py
ssb_dash_framework/__main__.py
ssb_dash_framework/assets/dashAgGridFunctions.js
ssb_dash_framework/assets/stylesheet.css
ssb_dash_framework/control/__init__.py
ssb_dash_framework/control/control_framework_base.py
ssb_dash_framework/modules/__init__.py
ssb_dash_framework/modules/aarsregnskap.py
ssb_dash_framework/modules/agg_dist_plotter.py
ssb_dash_framework/modules/altinn_control_view.py
ssb_dash_framework/modules/altinn_data_capture.py
ssb_dash_framework/modules/altinn_editor/__init__.py
ssb_dash_framework/modules/altinn_editor/altinn_editor_comment.py
ssb_dash_framework/modules/altinn_editor/altinn_editor_contact.py
ssb_dash_framework/modules/altinn_editor/altinn_editor_control.py
ssb_dash_framework/modules/altinn_editor/altinn_editor_history.py
ssb_dash_framework/modules/altinn_editor/altinn_editor_main_view.py
ssb_dash_framework/modules/altinn_editor/altinn_editor_primary_table.py
ssb_dash_framework/modules/altinn_editor/altinn_editor_submitted_forms.py
ssb_dash_framework/modules/altinn_editor/altinn_editor_supporting_table.py
ssb_dash_framework/modules/altinn_editor/altinn_editor_unit_details.py
ssb_dash_framework/modules/bofregistry.py
ssb_dash_framework/modules/building_blocks/__init__.py
ssb_dash_framework/modules/building_blocks/canvas.py
ssb_dash_framework/modules/building_blocks/figuredisplay.py
ssb_dash_framework/modules/building_blocks/map_display.py
ssb_dash_framework/modules/building_blocks/multimodule.py
ssb_dash_framework/modules/building_blocks/tables.py
ssb_dash_framework/modules/control.py
ssb_dash_framework/modules/freesearch.py
ssb_dash_framework/modules/hb_method.py
ssb_dash_framework/modules/macro_module.py
ssb_dash_framework/modules/parquet_editor.py
ssb_dash_framework/modules/pi_memorizer.py
ssb_dash_framework/modules/skjemapdfviewer.py
ssb_dash_framework/modules/visualizationbuilder.py
ssb_dash_framework/py.typed
ssb_dash_framework/setup/__init__.py
ssb_dash_framework/setup/app_setup.py
ssb_dash_framework-0.2.1.dist-info/LICENSE
ssb_dash_framework-0.2.1.dist-info/METADATA
ssb_dash_framework-0.2.1.dist-info/WHEEL
ssb_dash_framework-0.2.1.dist-info/entry_points.txt
ssb_dash_framework-0.2.1.dist-info/RECORD
