Metadata-Version: 2.3
Name: ssb-dash-framework
Version: 0.2.1
Summary: SSB Dash Framework
License: GPL-3.0
Author: Magnus Theodor Engh
Author-email: dor@ssb.no
Requires-Python: >=3.10,<4.0
Classifier: Development Status :: 4 - Beta
Classifier: License :: OSI Approved :: GNU General Public License v3 (GPLv3)
Classifier: Programming Language :: Python :: 3
Classifier: Programming Language :: Python :: 3.10
Classifier: Programming Language :: Python :: 3.11
Classifier: Programming Language :: Python :: 3.12
Classifier: Programming Language :: Python :: 3.13
Requires-Dist: click (>=8.0.1)
Requires-Dist: dapla-toolbelt (>=2.0.8,<5.0.0)
Requires-Dist: dash (>=3.3.0,<4.0.0)
Requires-Dist: dash-ag-grid (>=32.3.2,<33.0.0)
Requires-Dist: dash-bootstrap-components (>=2.0.4,<3.0.0)
Requires-Dist: dash-bootstrap-templates (>=2.1.0,<3.0.0)
Requires-Dist: duckdb (==1.3.2)
Requires-Dist: geopandas (>=1.1.1,<2.0.0)
Requires-Dist: ibis-framework[polars,postgres] (>=11.0.0,<12.0.0)
Requires-Dist: ipykernel (>=6.29.5,<7.0.0)
Requires-Dist: mpmath (>=1.3.0)
Requires-Dist: orjson (>=3.10.16,<4.0.0)
Requires-Dist: pandas (>=2.3.1,<3.0.0)
Requires-Dist: psycopg2-binary (>=2.9.10,<3.0.0)
Requires-Dist: rpy2 (>=3.6.4,<4.0.0)
Requires-Dist: rwrapr (>=0.9.1,<0.10.0)
Requires-Dist: sqlalchemy (>=2.0.43,<3.0.0)
Requires-Dist: ssb-eimerdb (>=0.2.6,<0.3.0)
Requires-Dist: ssb-poc-statlog-model (>=1.0.0,<2.0.0)
Project-URL: Changelog, https://github.com/statisticsnorway/ssb-dash-framework/releases
Project-URL: Documentation, https://statisticsnorway.github.io/ssb-dash-framework
Project-URL: Homepage, https://github.com/statisticsnorway/ssb-dash-framework
Project-URL: Repository, https://github.com/statisticsnorway/ssb-dash-framework
